backpropagate/__init__.py
backpropagate/__main__.py
backpropagate/checkpoints.py
backpropagate/cli.py
backpropagate/config.py
backpropagate/datasets.py
backpropagate/exceptions.py
backpropagate/export.py
backpropagate/feature_flags.py
backpropagate/gpu_safety.py
backpropagate/logging_config.py
backpropagate/multi_run.py
backpropagate/security.py
backpropagate/slao.py
backpropagate/theme.py
backpropagate/trainer.py
backpropagate/ui.py
backpropagate/ui_security.py
backpropagate-0.1.0.dist-info/METADATA
backpropagate-0.1.0.dist-info/WHEEL
backpropagate-0.1.0.dist-info/entry_points.txt
backpropagate-0.1.0.dist-info/licenses/LICENSE
backpropagate-0.1.0.dist-info/RECORD
