Metadata-Version: 2.4
Name: backpropagate
Version: 0.1.0
Summary: Production-ready headless LLM fine-tuning with smart defaults, Windows support, and modular architecture
Project-URL: Homepage, https://github.com/mikeyfrilot/backpropagate
Project-URL: Documentation, https://github.com/mikeyfrilot/backpropagate#readme
Project-URL: Repository, https://github.com/mikeyfrilot/backpropagate
Project-URL: Issues, https://github.com/mikeyfrilot/backpropagate/issues
Author: Mikey Frilot
License-Expression: MIT
License-File: LICENSE
Keywords: api,fine-tuning,headless,llm,lora,machine-learning,qlora,training,unsloth
Classifier: Development Status :: 3 - Alpha
Classifier: Intended Audience :: Developers
Classifier: Intended Audience :: Science/Research
Classifier: License :: OSI Approved :: MIT License
Classifier: Operating System :: OS Independent
Classifier: Programming Language :: Python :: 3
Classifier: Programming Language :: Python :: 3.10
Classifier: Programming Language :: Python :: 3.11
Classifier: Programming Language :: Python :: 3.12
Classifier: Topic :: Scientific/Engineering :: Artificial Intelligence
Classifier: Typing :: Typed
Requires-Python: >=3.10
Requires-Dist: accelerate>=0.25.0
Requires-Dist: bitsandbytes>=0.41.0
Requires-Dist: datasets>=2.14.0
Requires-Dist: packaging>=21.0
Requires-Dist: peft>=0.7.0
Requires-Dist: tenacity>=8.0.0
Requires-Dist: torch>=2.0.0
Requires-Dist: transformers>=4.36.0
Requires-Dist: trl>=0.7.0
Provides-Extra: dev
Requires-Dist: bandit>=1.7.0; extra == 'dev'
Requires-Dist: hypothesis>=6.100.0; extra == 'dev'
Requires-Dist: mutmut>=2.4.0; extra == 'dev'
Requires-Dist: mypy>=1.0.0; extra == 'dev'
Requires-Dist: packaging>=21.0; extra == 'dev'
Requires-Dist: pip-audit>=2.7.0; extra == 'dev'
Requires-Dist: pre-commit>=3.0.0; extra == 'dev'
Requires-Dist: pytest-asyncio>=0.21.0; extra == 'dev'
Requires-Dist: pytest-cov>=4.0.0; extra == 'dev'
Requires-Dist: pytest-mock>=3.10.0; extra == 'dev'
Requires-Dist: pytest-timeout>=2.3.0; extra == 'dev'
Requires-Dist: pytest-xdist>=3.5.0; extra == 'dev'
Requires-Dist: pytest>=7.0.0; extra == 'dev'
Requires-Dist: ruff>=0.1.0; extra == 'dev'
Requires-Dist: safety>=2.3.0; extra == 'dev'
Provides-Extra: export
Requires-Dist: llama-cpp-python>=0.2.0; extra == 'export'
Provides-Extra: full
Requires-Dist: cryptography>=42.0.0; extra == 'full'
Requires-Dist: gradio>=5.6.0; extra == 'full'
Requires-Dist: llama-cpp-python>=0.2.0; extra == 'full'
Requires-Dist: opentelemetry-api>=1.20.0; extra == 'full'
Requires-Dist: opentelemetry-sdk>=1.20.0; extra == 'full'
Requires-Dist: psutil>=5.9.0; extra == 'full'
Requires-Dist: pydantic-settings>=2.0.0; extra == 'full'
Requires-Dist: pydantic>=2.0.0; extra == 'full'
Requires-Dist: pyjwt>=2.8.0; extra == 'full'
Requires-Dist: structlog>=24.1.0; extra == 'full'
Requires-Dist: unsloth>=2024.1; extra == 'full'
Requires-Dist: wandb>=0.15.0; extra == 'full'
Provides-Extra: logging
Requires-Dist: structlog>=24.1.0; extra == 'logging'
Provides-Extra: monitoring
Requires-Dist: psutil>=5.9.0; extra == 'monitoring'
Requires-Dist: wandb>=0.15.0; extra == 'monitoring'
Provides-Extra: observability
Requires-Dist: opentelemetry-api>=1.20.0; extra == 'observability'
Requires-Dist: opentelemetry-sdk>=1.20.0; extra == 'observability'
Provides-Extra: production
Requires-Dist: cryptography>=42.0.0; extra == 'production'
Requires-Dist: gradio>=5.6.0; extra == 'production'
Requires-Dist: pydantic-settings>=2.0.0; extra == 'production'
Requires-Dist: pydantic>=2.0.0; extra == 'production'
Requires-Dist: pyjwt>=2.8.0; extra == 'production'
Requires-Dist: structlog>=24.1.0; extra == 'production'
Requires-Dist: unsloth>=2024.1; extra == 'production'
Provides-Extra: security
Requires-Dist: cryptography>=42.0.0; extra == 'security'
Requires-Dist: pyjwt>=2.8.0; extra == 'security'
Provides-Extra: standard
Requires-Dist: gradio>=5.6.0; extra == 'standard'
Requires-Dist: unsloth>=2024.1; extra == 'standard'
Provides-Extra: ui
Requires-Dist: gradio>=5.6.0; extra == 'ui'
Provides-Extra: unsloth
Requires-Dist: unsloth>=2024.1; extra == 'unsloth'
Provides-Extra: validation
Requires-Dist: pydantic-settings>=2.0.0; extra == 'validation'
Requires-Dist: pydantic>=2.0.0; extra == 'validation'
